pds_doi_service/VERSION.txt
pds_doi_service/__init__.py
pds_doi_service/test.py
pds_doi_service/api/__init__.py
pds_doi_service/api/__main__.py
pds_doi_service/api/encoder.py
pds_doi_service/api/util.py
pds_doi_service/api/controllers/__init__.py
pds_doi_service/api/controllers/authentication.py
pds_doi_service/api/controllers/dois_controller.py
pds_doi_service/api/models/__init__.py
pds_doi_service/api/models/base_model_.py
pds_doi_service/api/models/doi_record.py
pds_doi_service/api/models/doi_summary.py
pds_doi_service/api/models/label_payload.py
pds_doi_service/api/models/labels_payload.py
pds_doi_service/api/swagger/swagger.yaml
pds_doi_service/api/test/__init__.py
pds_doi_service/api/test/_base.py
pds_doi_service/api/test/test_dois_controller.py
pds_doi_service/api/test/data/bundle_in.xml
pds_doi_service/api/test/data/bundle_in_with_contributors.xml
pds_doi_service/api/test/data/pending_dois.db
pds_doi_service/api/test/data/test.db
pds_doi_service/api/test/data/datacite/draft_record
pds_doi_service/api/test/data/datacite/output.json
pds_doi_service/api/test/data/datacite/release_record
pds_doi_service/api/test/data/datacite/reserve_record
pds_doi_service/api/test/data/osti/draft_record
pds_doi_service/api/test/data/osti/error_record
pds_doi_service/api/test/data/osti/output.xml
pds_doi_service/api/test/data/osti/release_record
pds_doi_service/api/test/data/osti/reserve_record
pds_doi_service/core/__init__.py
pds_doi_service/core/test_utils.py
pds_doi_service/core/actions/__init__.py
pds_doi_service/core/actions/action.py
pds_doi_service/core/actions/check.py
pds_doi_service/core/actions/list.py
pds_doi_service/core/actions/release.py
pds_doi_service/core/actions/reserve.py
pds_doi_service/core/actions/update.py
pds_doi_service/core/actions/roundup/__init__.py
pds_doi_service/core/actions/roundup/email.py
pds_doi_service/core/actions/roundup/enumerate.py
pds_doi_service/core/actions/roundup/metadata.py
pds_doi_service/core/actions/roundup/output.py
pds_doi_service-3.0.3.dist-info/licenses/LICENSE.md
pds_doi_service-3.0.3.dist-info/licenses/NOTICE.txt
pds_doi_service-3.0.3.dist-info/METADATA
pds_doi_service-3.0.3.dist-info/WHEEL
pds_doi_service-3.0.3.dist-info/entry_points.txt
pds_doi_service-3.0.3.dist-info/top_level.txt
pds_doi_service-3.0.3.dist-info/RECORD
