Metadata-Version: 2.4
Name: pds-doi-service
Version: 3.0.3
Summary: Digital Object Identifier service for the Planetary Data System
Home-page: https://github.com/NASA-PDS/pds-doi-service
Download-URL: https://github.com/NASA-PDS/pds-doi-service/releases/
Author: PDS
Author-email: pds_operator@jpl.nasa.gov
License: apache-2.0
Keywords: pds,doi,osti,dataCite
Classifier: Development Status :: 5 - Production/Stable
Classifier: Environment :: Web Environment
Classifier: Framework :: Flask
Classifier: Intended Audience :: Science/Research
Classifier: Operating System :: OS Independent
Classifier: Programming Language :: Python :: 3
Classifier: Programming Language :: Python :: 3.12
Classifier: Programming Language :: Python :: 3.13
Classifier: Topic :: Scientific/Engineering
Requires-Python: >=3.12
License-File: LICENSE.md
License-File: NOTICE.txt
Requires-Dist: a2wsgi~=1.10.8
Requires-Dist: appdirs~=1.4.4
Requires-Dist: bs4==0.0.1
Requires-Dist: certifi==2024.8.30
Requires-Dist: chardet~=5.2.0
Requires-Dist: connexion[swagger-ui]~=2.7.0
Requires-Dist: dataclasses==0.7; python_version <= "3.6"
Requires-Dist: distlib~=0.3.7
Requires-Dist: fabric~=3.0
Requires-Dist: filelock~=3.12.3
Requires-Dist: Flask~=2.2.2
Requires-Dist: flask-cors==3.0.9
Requires-Dist: idna==3.10
Requires-Dist: itsdangerous==2.0.1
Requires-Dist: jinja2==3.1.4
Requires-Dist: jsonschema<4.0.0,>=3.0.0
Requires-Dist: lxml==6.0.0
Requires-Dist: nltk==3.5
Requires-Dist: numpy==2.2.3
Requires-Dist: openapi-schema-validator~=0.1.5
Requires-Dist: openpyxl~=3.1.0
Requires-Dist: packaging>=21.0
Requires-Dist: pandas==2.3.0
Requires-Dist: python-dateutil~=2.9.0.post0
Requires-Dist: python-jose[cryptography]
Requires-Dist: pytz>=2024.1
Requires-Dist: requests~=2.32.3
Requires-Dist: setuptools>=65.0.0
Requires-Dist: six~=1.16.0
Requires-Dist: soupsieve~=2.6
Requires-Dist: urllib3~=2.2.3
Requires-Dist: waitress==2.0.0
Requires-Dist: Werkzeug~=2.2.2
Requires-Dist: wheel
Requires-Dist: xlrd>=1.2
Requires-Dist: xmlschema>=2.0.0
Requires-Dist: xmltodict~=0.13.0
Requires-Dist: zipp~=3.20.2
Provides-Extra: dev
Requires-Dist: aiosmtpd~=1.4.6; extra == "dev"
Requires-Dist: build~=1.2.2; extra == "dev"
Requires-Dist: flake8~=7.3.0; extra == "dev"
Requires-Dist: flake8-bugbear~=24.12.12; extra == "dev"
Requires-Dist: flake8-docstrings~=1.7.0; extra == "dev"
Requires-Dist: pep8-naming~=0.14.1; extra == "dev"
Requires-Dist: pydocstyle~=6.3.0; extra == "dev"
Requires-Dist: coverage~=7.6.1; extra == "dev"
Requires-Dist: pytest~=7.4.0; extra == "dev"
Requires-Dist: pytest-cov~=4.1.0; extra == "dev"
Requires-Dist: pytest-watch~=4.2.0; extra == "dev"
Requires-Dist: pytest-xdist~=3.6.1; extra == "dev"
Requires-Dist: pre-commit~=3.3.3; extra == "dev"
Requires-Dist: sphinx~=8.2.3; extra == "dev"
Requires-Dist: sphinx-rtd-theme~=3.0.2; extra == "dev"
Requires-Dist: types-setuptools~=68.1.0.0; extra == "dev"
Requires-Dist: sphinxcontrib-napoleon~=0.7; extra == "dev"
Requires-Dist: tox>=4.0; extra == "dev"
Requires-Dist: flask_testing~=0.8.0; extra == "dev"
Requires-Dist: sphinx-rtd-theme~=3.0.2; extra == "dev"
Requires-Dist: sphinx-argparse~=0.2.5; extra == "dev"
Requires-Dist: behave~=1.2.6; extra == "dev"
Requires-Dist: allure-behave~=2.8.13; extra == "dev"
Requires-Dist: behave-testrail-reporter~=0.4.0; extra == "dev"
Requires-Dist: pygit2~=1.18.2; extra == "dev"
Requires-Dist: lxml-stubs~=0.5.1; extra == "dev"
Requires-Dist: pandas-stubs~=2.0.1.230501; extra == "dev"
Requires-Dist: types-flask~=1.1.6; extra == "dev"
Requires-Dist: types-jsonschema~=4.23.0.20240813; extra == "dev"
Requires-Dist: types-python-dateutil~=2.9.0.20240906; extra == "dev"
Requires-Dist: types-requests~=2.32.0.20240914; extra == "dev"
Requires-Dist: types-six~=1.16.21.20240513; extra == "dev"
Requires-Dist: types-waitress~=3.0.0.20240423; extra == "dev"
Requires-Dist: virtualenv~=20.24.3; extra == "dev"
Dynamic: download-url
Dynamic: license-file
